youthon/__init__.py
youthon/channel.py
youthon/funcs.py
youthon/playlist.py
youthon/video.py
youthon-0.5.0.dist-info/licenses/LICENSE
youthon-0.5.0.dist-info/METADATA
youthon-0.5.0.dist-info/WHEEL
youthon-0.5.0.dist-info/RECORD
