Metadata-Version: 2.4
Name: youthon
Version: 0.5.0
Summary: A lightweight YouTube data scraper.
License: MIT
License-File: LICENSE
Author: anekobtw
Requires-Python: >=3.9
Classifier: License :: OSI Approved :: MIT License
Classifier: Programming Language :: Python :: 3
Classifier: Programming Language :: Python :: 3.9
Classifier: Programming Language :: Python :: 3.10
Classifier: Programming Language :: Python :: 3.11
Classifier: Programming Language :: Python :: 3.12
Classifier: Programming Language :: Python :: 3.13
Classifier: Programming Language :: Python :: 3.14
Requires-Dist: beautifulsoup4 (==4.12.3)
Requires-Dist: colorama (>=0.4.6,<0.5.0)
Requires-Dist: requests (>=2.32.5,<3.0.0)
Project-URL: Repository, https://github.com/anekobtw/youthon
